CHANGES.md
LICENSE
MANIFEST.in
README.md
setup.py
mp3_zing_downloader/__init__.py
mp3_zing_downloader/crawler.py
mp3_zing_downloader/spiders.py
mp3_zing_downloader.egg-info/PKG-INFO
mp3_zing_downloader.egg-info/SOURCES.txt
mp3_zing_downloader.egg-info/dependency_links.txt
mp3_zing_downloader.egg-info/entry_points.txt
mp3_zing_downloader.egg-info/requires.txt
mp3_zing_downloader.egg-info/top_level.txt