Metadata-Version: 1.0
Name: mp3-zing-downloader
Version: 1.3.3
Summary: Downloader to download music from mp3.zing.vn
Home-page: https://github.com/tarzanjw/mp3_zing_downloader
Author: Hoc .T Do
Author-email: hoc3010@gmail.com
License: LICENSE
Platform: UNKNOWN
